simple_pipelines/__init__.py
simple_pipelines/logging/__init__.py
simple_pipelines/visualize/__init__.py
simple_pipelines-0.1.4.dist-info/METADATA
simple_pipelines-0.1.4.dist-info/WHEEL
simple_pipelines-0.1.4.dist-info/RECORD
