Metadata-Version: 2.3
Name: simple-pipelines
Version: 0.1.4
Summary: Simple but effective data pipeline builder
Author: Mathieu Sherburne
Author-email: mathieusherburne@outlook.com
Requires-Python: >=3.9,<4.0
Classifier: Programming Language :: Python :: 3
Classifier: Programming Language :: Python :: 3.9
Classifier: Programming Language :: Python :: 3.10
Classifier: Programming Language :: Python :: 3.11
Classifier: Programming Language :: Python :: 3.12
Classifier: Programming Language :: Python :: 3.13
Requires-Dist: networkx (>=2.4)
Requires-Dist: pandas (>=2.1.0,<3.0.0)
Requires-Dist: plotly (>=6.0.0,<7.0.0)
